lib/__init__.py
lib/icpms/__init__.py
lib/srm/__init__.py
notebooks/__init__.py
pysills/__init__.py
pysills/main.py
pysills/pysills_app.py
pysills/adapters/__init__.py
pysills/cli/__init__.py
pysills/core/__init__.py
pysills/core/chemistry/__init__.py
pysills/core/concentrations/__init__.py
pysills/core/inclusion_analysis/__init__.py
pysills/core/intensities/__init__.py
pysills/core/io/__init__.py
pysills/core/mathematics/__init__.py
pysills/core/mineral_analysis/__init__.py
pysills/core/sensitivities/__init__.py
pysills/gui/__init__.py
pysills/gui/colors.py
pysills/legacy/__init__.py
pysills/legacy/main.py
pysills/legacy/pysills_app.py
pysills/legacy/lib/__init__.py
pysills/legacy/lib/demo_files/Example_Input_File.csv
pysills/legacy/lib/demo_files/demo_fi01.csv
pysills/legacy/lib/demo_files/demo_fi02.csv
pysills/legacy/lib/demo_files/demo_fi03.csv
pysills/legacy/lib/demo_files/demo_fi04.csv
pysills/legacy/lib/demo_files/demo_fi05.csv
pysills/legacy/lib/demo_files/demo_fi06.csv
pysills/legacy/lib/demo_files/demo_fi07.csv
pysills/legacy/lib/demo_files/demo_fi08.csv
pysills/legacy/lib/demo_files/demo_fi09.csv
pysills/legacy/lib/demo_files/demo_fi10.csv
pysills/legacy/lib/demo_files/demo_fi11.csv
pysills/legacy/lib/demo_files/demo_fi12.csv
pysills/legacy/lib/demo_files/demo_fi13.csv
pysills/legacy/lib/demo_files/demo_is_fi.csv
pysills/legacy/lib/demo_files/demo_is_ma.csv
pysills/legacy/lib/demo_files/demo_is_mi.csv
pysills/legacy/lib/demo_files/demo_ma01.csv
pysills/legacy/lib/demo_files/demo_ma02.csv
pysills/legacy/lib/demo_files/demo_ma03.csv
pysills/legacy/lib/demo_files/demo_ma04.csv
pysills/legacy/lib/demo_files/demo_ma05.csv
pysills/legacy/lib/demo_files/demo_ma06.csv
pysills/legacy/lib/demo_files/demo_ma07.csv
pysills/legacy/lib/demo_files/demo_ma08.csv
pysills/legacy/lib/demo_files/demo_ma09.csv
pysills/legacy/lib/demo_files/demo_ma10.csv
pysills/legacy/lib/demo_files/demo_ma11.csv
pysills/legacy/lib/demo_files/demo_ma12.csv
pysills-1.0.93.dist-info/LICENSE
pysills-1.0.93.dist-info/METADATA
pysills-1.0.93.dist-info/WHEEL
pysills-1.0.93.dist-info/entry_points.txt
pysills-1.0.93.dist-info/top_level.txt
pysills-1.0.93.dist-info/RECORD
